odoo8_addon_account_asset_depr_line_cancel-8.0.1.0.0-py2.7-nspkg.pth
odoo_addons/account_asset_depr_line_cancel/__openerp__.py
odoo_addons/account_asset_depr_line_cancel/__init__.py
odoo_addons/account_asset_depr_line_cancel/README.rst
odoo_addons/account_asset_depr_line_cancel/models/__init__.py
odoo_addons/account_asset_depr_line_cancel/models/account_asset_asset.py
odoo_addons/account_asset_depr_line_cancel/views/account_asset_asset_view.xml
odoo_addons/account_asset_depr_line_cancel/static/description/icon.svg
odoo_addons/account_asset_depr_line_cancel/static/description/icon.png
odoo8_addon_account_asset_depr_line_cancel-8.0.1.0.0.dist-info/top_level.txt
odoo8_addon_account_asset_depr_line_cancel-8.0.1.0.0.dist-info/WHEEL
odoo8_addon_account_asset_depr_line_cancel-8.0.1.0.0.dist-info/RECORD
odoo8_addon_account_asset_depr_line_cancel-8.0.1.0.0.dist-info/metadata.json
odoo8_addon_account_asset_depr_line_cancel-8.0.1.0.0.dist-info/DESCRIPTION.rst
odoo8_addon_account_asset_depr_line_cancel-8.0.1.0.0.dist-info/METADATA
odoo8_addon_account_asset_depr_line_cancel-8.0.1.0.0.dist-info/namespace_packages.txt
