Metadata-Version: 2.0
Name: odoo8-addon-account-asset-depr-line-cancel
Version: 8.0.1.0.0
Summary: Assets Management - Cancel button
Home-page: http://www.serviciosbaeza.com
Author: Tecnativa, Odoo Community Association (OCA)
Author-email: support@odoo-community.org
License: AGPL-3
Platform: UNKNOWN
Requires-Dist: odoo (<9.0a,>=8.0a)
Classifier: Programming Language :: Python :: 2.7
Classifier: Framework :: Odoo
Classifier: License :: OSI Approved :: GNU Affero General Public License v3
